{"expireTime":9007200857877015000,"key":"gatsby-plugin-mdx-entire-payload-8948c0c96ce6bb731eb3b968b39df125-","val":{"mdast":{"type":"root","children":[{"type":"heading","depth":2,"children":[{"type":"text","value":"Get in touch","position":{"start":{"line":1,"column":4,"offset":3},"end":{"line":1,"column":16,"offset":15},"indent":[]}}],"position":{"start":{"line":1,"column":1,"offset":0},"end":{"line":1,"column":16,"offset":15},"indent":[]}},{"type":"paragraph","children":[{"type":"text","value":"If you want to say just Hi or follow me for my activities, my social platforms : ","position":{"start":{"line":3,"column":1,"offset":19},"end":{"line":3,"column":82,"offset":100},"indent":[]}},{"type":"jsx","value":"<a href=\"https://www.instagram.com/raebpn/\" target=\"_blank\">","position":{"start":{"line":3,"column":82,"offset":100},"end":{"line":3,"column":142,"offset":160},"indent":[]}},{"type":"text","value":"Instagram","position":{"start":{"line":3,"column":142,"offset":160},"end":{"line":3,"column":151,"offset":169},"indent":[]}},{"type":"jsx","value":"</a>","position":{"start":{"line":3,"column":151,"offset":169},"end":{"line":3,"column":155,"offset":173},"indent":[]}},{"type":"text","value":" and ","position":{"start":{"line":3,"column":155,"offset":173},"end":{"line":3,"column":160,"offset":178},"indent":[]}},{"type":"jsx","value":"<a href=\"https://www.facebook.com/profile.php?id=100009164750493\" target = \"_blank\">","position":{"start":{"line":3,"column":160,"offset":178},"end":{"line":3,"column":244,"offset":262},"indent":[]}},{"type":"text","value":" Facebook","position":{"start":{"line":3,"column":244,"offset":262},"end":{"line":3,"column":253,"offset":271},"indent":[]}},{"type":"jsx","value":"</a>","position":{"start":{"line":3,"column":253,"offset":271},"end":{"line":3,"column":257,"offset":275},"indent":[]}}],"position":{"start":{"line":3,"column":1,"offset":19},"end":{"line":3,"column":257,"offset":275},"indent":[]}},{"type":"paragraph","children":[{"type":"text","value":"You can also connect to me via ","position":{"start":{"line":5,"column":1,"offset":279},"end":{"line":5,"column":32,"offset":310},"indent":[]}},{"type":"jsx","value":"<a href=\"https://www.linkedin.com/in/bipin-rai-b7011296/\" target=\"_blank\">","position":{"start":{"line":5,"column":32,"offset":310},"end":{"line":5,"column":106,"offset":384},"indent":[]}},{"type":"text","value":"LinkedIn","position":{"start":{"line":5,"column":106,"offset":384},"end":{"line":5,"column":114,"offset":392},"indent":[]}},{"type":"jsx","value":"</a>","position":{"start":{"line":5,"column":114,"offset":392},"end":{"line":5,"column":118,"offset":396},"indent":[]}},{"type":"text","value":" and ","position":{"start":{"line":5,"column":118,"offset":396},"end":{"line":5,"column":123,"offset":401},"indent":[]}},{"type":"jsx","value":"<a href=\"https://github.com/raibpn\" target = \"_blank\">","position":{"start":{"line":5,"column":123,"offset":401},"end":{"line":5,"column":177,"offset":455},"indent":[]}},{"type":"text","value":" GitHub","position":{"start":{"line":5,"column":177,"offset":455},"end":{"line":5,"column":184,"offset":462},"indent":[]}},{"type":"jsx","value":"</a>","position":{"start":{"line":5,"column":184,"offset":462},"end":{"line":5,"column":188,"offset":466},"indent":[]}},{"type":"text","value":"\nOr you can write to me at ","position":{"start":{"line":5,"column":188,"offset":466},"end":{"line":6,"column":27,"offset":494},"indent":[1]}},{"type":"link","title":null,"url":"mailto:saayan.rai@gmail.com","children":[{"type":"text","value":"saayan.rai@gmail.com","position":{"start":{"line":6,"column":27,"offset":494},"end":{"line":6,"column":47,"offset":514},"indent":[]}}],"position":{"start":{"line":6,"column":27,"offset":494},"end":{"line":6,"column":47,"offset":514},"indent":[]}}],"position":{"start":{"line":5,"column":1,"offset":279},"end":{"line":6,"column":47,"offset":514},"indent":[1]}},{"type":"export","value":"export const _frontmatter = {}","position":{"start":{"line":8,"column":1,"offset":516},"end":{"line":8,"column":31,"offset":546},"indent":[]}}],"position":{"start":{"line":1,"column":1,"offset":0},"end":{"line":8,"column":31,"offset":546}}},"scopeImports":[],"scopeIdentifiers":[],"rawMDXOutput":"/* @jsx mdx */\nimport { mdx } from '@mdx-js/react';\n/* @jsx mdx */\n\nexport const _frontmatter = {};\n\nconst layoutProps = {\n  _frontmatter\n};\nconst MDXLayout = \"wrapper\"\nexport default function MDXContent({\n  components,\n  ...props\n}) {\n  return <MDXLayout {...layoutProps} {...props} components={components} mdxType=\"MDXLayout\">\n    <h2>{`Get in touch`}</h2>\n    <p>{`If you want to say just Hi or follow me for my activities, my social platforms : `}<a href=\"https://www.instagram.com/raebpn/\" target=\"_blank\">{`Instagram`}</a>{` and `}<a href=\"https://www.facebook.com/profile.php?id=100009164750493\" target=\"_blank\">{` Facebook`}</a></p>\n    <p>{`You can also connect to me via `}<a href=\"https://www.linkedin.com/in/bipin-rai-b7011296/\" target=\"_blank\">{`LinkedIn`}</a>{` and `}<a href=\"https://github.com/raibpn\" target=\"_blank\">{` GitHub`}</a>{`\nOr you can write to me at `}<a parentName=\"p\" {...{\n        \"href\": \"mailto:saayan.rai@gmail.com\"\n      }}>{`saayan.rai@gmail.com`}</a></p>\n\n    </MDXLayout>;\n}\n\n;\nMDXContent.isMDXComponent = true;"}}